README.md
setup.py
applehttp2push/__init__.py
applehttp2push/core.py
applehttp2push.egg-info/PKG-INFO
applehttp2push.egg-info/SOURCES.txt
applehttp2push.egg-info/dependency_links.txt
applehttp2push.egg-info/requires.txt
applehttp2push.egg-info/top_level.txt