Metadata-Version: 1.0
Name: applehttp2push
Version: 1.0.0
Summary: 一个基于python2和http2的苹果推送SDK，基于yubang的修改。增加文件验证密码，区分推送标题和主体，增加声音控制。
Home-page: https://github.com/geyouwen/applehttp2push
Author: geyouwen
Author-email: 690591423@qq.com
License: UNKNOWN
Platform: UNKNOWN
